<?xml version = '1.0' encoding = 'UTF-8'?>
<TableProxyOraclev12c class="oracle.dbtools.crest.model.design.storage.oracle.v12c.TableProxyOraclev12c" name="PROFESOR" directorySegmentName="seg_0" id="81CFD542-306C-D41D-2F5E-BFB6A715CF29">
<createdBy>rpadron</createdBy>
<createdTime>2020-03-10 16:16:52 UTC</createdTime>
<ownerDesignName>fundauc-prod</ownerDesignName>
<schemaObject>E79B8DC2-2292-A202-640F-D21DD6B2A19B</schemaObject>
<logging>YES</logging>
<partitionedRowMovement>DISABLE</partitionedRowMovement>
<segment>7D3E360F-D6BC-A999-6E53-8BE252D2159C</segment>
<tableSpace>FF2D8F0B-D353-A194-C6D7-D43A9B1C2FBF</tableSpace>
<temporaryChanged>false</temporaryChanged>
<accessDriverType>oracle_loader</accessDriverType>
<rejectLimit></rejectLimit>
<inMemory>NO</inMemory>
<columnProxies itemClass="oracle.dbtools.crest.model.design.storage.oracle.v12c.ColumnProxyOraclev12c">
<ColumnProxy name="EDO_CIVIL" id="1E4033BD-99A1-1720-08DD-633E7154B707">
<createdBy>rpadron</createdBy>
<createdTime>2020-03-10 16:16:55 UTC</createdTime>
<ownerDesignName>fundauc-prod</ownerDesignName>
</ColumnProxy>
<ColumnProxy name="NACIONALIDAD" id="28F29D28-13E2-BAD5-DD46-99ED536BC1F0">
<createdBy>rpadron</createdBy>
<createdTime>2020-03-10 16:16:55 UTC</createdTime>
<ownerDesignName>fundauc-prod</ownerDesignName>
<nncEnable>NO</nncEnable>
<nncValidate>NO</nncValidate>
</ColumnProxy>
<ColumnProxy name="PROFESION" id="2D4D1DF4-8F58-ACAA-C233-59379FA38075">
<createdBy>rpadron</createdBy>
<createdTime>2020-03-10 16:16:55 UTC</createdTime>
<ownerDesignName>fundauc-prod</ownerDesignName>
</ColumnProxy>
<ColumnProxy name="ESTADO" id="3C9D4013-1AEA-3C22-3125-1E7CD511319D">
<createdBy>rpadron</createdBy>
<createdTime>2020-03-10 16:16:55 UTC</createdTime>
<ownerDesignName>fundauc-prod</ownerDesignName>
</ColumnProxy>
<ColumnProxy name="TELF_CEL" id="4F617F64-73FB-6675-B210-A0305CA6381F">
<createdBy>rpadron</createdBy>
<createdTime>2020-03-10 16:16:55 UTC</createdTime>
<ownerDesignName>fundauc-prod</ownerDesignName>
</ColumnProxy>
<ColumnProxy name="CEDULA_PROF" id="51BB2605-1C7A-3458-A0C5-905AA277FD43">
<createdBy>rpadron</createdBy>
<createdTime>2020-03-10 16:16:55 UTC</createdTime>
<ownerDesignName>fundauc-prod</ownerDesignName>
</ColumnProxy>
<ColumnProxy name="STATUS" id="5A76E8EA-65AD-F8AC-D54D-E6670A7B4130">
<createdBy>rpadron</createdBy>
<createdTime>2020-03-10 16:16:55 UTC</createdTime>
<ownerDesignName>fundauc-prod</ownerDesignName>
</ColumnProxy>
<ColumnProxy name="TELF_HAB" id="78AA58A1-5C42-24D8-35F6-4E8C9CD2AF0E">
<createdBy>rpadron</createdBy>
<createdTime>2020-03-10 16:16:55 UTC</createdTime>
<ownerDesignName>fundauc-prod</ownerDesignName>
</ColumnProxy>
<ColumnProxy name="APELLIDO" id="837545F0-A315-A9D4-D11F-3136DCD6972E">
<createdBy>rpadron</createdBy>
<createdTime>2020-03-10 16:16:55 UTC</createdTime>
<ownerDesignName>fundauc-prod</ownerDesignName>
</ColumnProxy>
<ColumnProxy name="DIRECCION" id="9D05829D-79DB-5D9A-BD62-9E4AEDF8BA24">
<createdBy>rpadron</createdBy>
<createdTime>2020-03-10 16:16:55 UTC</createdTime>
<ownerDesignName>fundauc-prod</ownerDesignName>
</ColumnProxy>
<ColumnProxy name="ID_TIPO_PROF" id="A39E9860-D64E-BE98-072C-F14773FE0542">
<createdBy>rpadron</createdBy>
<createdTime>2020-03-10 16:16:55 UTC</createdTime>
<ownerDesignName>fundauc-prod</ownerDesignName>
</ColumnProxy>
<ColumnProxy name="RIF" id="A7C08451-0C33-8AF6-2249-8D3CC6DB32BD">
<createdBy>rpadron</createdBy>
<createdTime>2020-03-10 16:16:55 UTC</createdTime>
<ownerDesignName>fundauc-prod</ownerDesignName>
</ColumnProxy>
<ColumnProxy name="GRADO_INS" id="B20208F6-5DBC-9722-93CA-8A5ED5A13A53">
<createdBy>rpadron</createdBy>
<createdTime>2020-03-10 16:16:55 UTC</createdTime>
<ownerDesignName>fundauc-prod</ownerDesignName>
</ColumnProxy>
<ColumnProxy name="EMAIL" id="D69D8A6E-EA83-738A-B7D1-22D45F5A1643">
<createdBy>rpadron</createdBy>
<createdTime>2020-03-10 16:16:55 UTC</createdTime>
<ownerDesignName>fundauc-prod</ownerDesignName>
</ColumnProxy>
<ColumnProxy name="CIUDAD" id="D7F074FE-8C2E-96E1-9E81-8816CBAE3D67">
<createdBy>rpadron</createdBy>
<createdTime>2020-03-10 16:16:55 UTC</createdTime>
<ownerDesignName>fundauc-prod</ownerDesignName>
</ColumnProxy>
<ColumnProxy name="FECHA_NAC" id="DC0B6C17-EDF4-1FC7-8E97-67412161AB8A">
<createdBy>rpadron</createdBy>
<createdTime>2020-03-10 16:16:55 UTC</createdTime>
<ownerDesignName>fundauc-prod</ownerDesignName>
</ColumnProxy>
<ColumnProxy name="ZONA" id="DF87D052-DA04-9595-7DEE-D4C78A5A8AF7">
<createdBy>rpadron</createdBy>
<createdTime>2020-03-10 16:16:55 UTC</createdTime>
<ownerDesignName>fundauc-prod</ownerDesignName>
</ColumnProxy>
<ColumnProxy name="SEDE" id="E9976920-11F1-6310-6A12-B0AC9B923140">
<createdBy>rpadron</createdBy>
<createdTime>2020-03-10 16:16:55 UTC</createdTime>
<ownerDesignName>fundauc-prod</ownerDesignName>
</ColumnProxy>
<ColumnProxy name="SEXO" id="EA210E28-B0BC-7346-1D46-00E31E23403E">
<createdBy>rpadron</createdBy>
<createdTime>2020-03-10 16:16:55 UTC</createdTime>
<ownerDesignName>fundauc-prod</ownerDesignName>
</ColumnProxy>
<ColumnProxy name="NOMBRE" id="F9F99061-C4B2-20E7-764E-91A66759F675">
<createdBy>rpadron</createdBy>
<createdTime>2020-03-10 16:16:55 UTC</createdTime>
<ownerDesignName>fundauc-prod</ownerDesignName>
<nncEnable>NO</nncEnable>
<nncValidate>NO</nncValidate>
</ColumnProxy>
</columnProxies>
<indexProxies>
<IndexProxy class="oracle.dbtools.crest.model.design.storage.oracle.v10g.IndexProxyOraclev10g" name="SYS_C0018599" id="36BB593F-A549-AE98-2A4A-2458F87B1DB7">
<createdBy>rpadron</createdBy>
<createdTime>2020-03-10 16:16:59 UTC</createdTime>
<ownerDesignName>fundauc-prod</ownerDesignName>
<schemaObject>E79B8DC2-2292-A202-640F-D21DD6B2A19B</schemaObject>
<segment>FC88B50F-E750-53C1-AB19-6A3E4046585D</segment>
<tableSpace>FF2D8F0B-D353-A194-C6D7-D43A9B1C2FBF</tableSpace>
</IndexProxy>
</indexProxies>
<primaryKeys>
<PrimaryKey class="oracle.dbtools.crest.model.design.storage.oracle.v10g.PKProxyOraclev10g" name="PROFESOR_PK" id="C93DBB63-971F-B26F-667D-535E0B2D3F76">
<createdBy>rpadron</createdBy>
<createdTime>2020-03-10 16:17:04 UTC</createdTime>
<ownerDesignName>fundauc-prod</ownerDesignName>
<segment>FC88B50F-E750-53C1-AB19-6A3E4046585D</segment>
<tableSpace>FF2D8F0B-D353-A194-C6D7-D43A9B1C2FBF</tableSpace>
<existingIndex>36BB593F-A549-AE98-2A4A-2458F87B1DB7</existingIndex>
<indexSegment>FC88B50F-E750-53C1-AB19-6A3E4046585D</indexSegment>
<indexSort>SORTED</indexSort>
<usingIndex>BY INDEX NAME</usingIndex>
</PrimaryKey>
</primaryKeys>
</TableProxyOraclev12c>