<?xml version = '1.0' encoding = 'UTF-8'?>
<SegmentOraclev10g class="oracle.dbtools.crest.model.design.storage.oracle.v10g.SegmentOraclev10g" name="Storage64" directorySegmentName="seg_0" id="A4E2B93A-7B37-50DC-F17F-B568BCC09862">
<createdBy>rpadron</createdBy>
<createdTime>2020-03-10 16:16:59 UTC</createdTime>
<ownerDesignName>fundauc-prod</ownerDesignName>
<initrans>2</initrans>
<maxTrans>255</maxTrans>
<scInitialExtent>262144</scInitialExtent>
<scMaxExtents>2147483645</scMaxExtents>
<scNextExtent>1048576</scNextExtent>
</SegmentOraclev10g>