<?xml version = '1.0' encoding = 'UTF-8'?>
<TableProxyOraclev12c class="oracle.dbtools.crest.model.design.storage.oracle.v12c.TableProxyOraclev12c" name="METODOS" directorySegmentName="seg_0" id="4BF0E7F6-DA35-84DB-837A-1450BFBB8814">
<createdBy>padron</createdBy>
<createdTime>2019-07-05 12:28:53 UTC</createdTime>
<ownerDesignName>CES-FUNDAUC</ownerDesignName>
<schemaObject>FCF41941-BA25-8770-CD3F-F4AB582A1881</schemaObject>
<logging>YES</logging>
<partitionedRowMovement>DISABLE</partitionedRowMovement>
<segment>10401428-D454-BA1D-9354-9CED063AB4CD</segment>
<tableSpace>C6CAF53F-0023-9370-2192-887C9EC71552</tableSpace>
<temporaryChanged>false</temporaryChanged>
<accessDriverType>oracle_loader</accessDriverType>
<rejectLimit></rejectLimit>
<inMemory>NO</inMemory>
<columnProxies itemClass="oracle.dbtools.crest.model.design.storage.oracle.v12c.ColumnProxyOraclev12c">
<ColumnProxy name="EVALUACIONES" id="192E6E23-D890-4674-2129-65A8A4B74950">
<createdBy>padron</createdBy>
<createdTime>2019-07-05 12:28:54 UTC</createdTime>
<ownerDesignName>CES-FUNDAUC</ownerDesignName>
</ColumnProxy>
<ColumnProxy name="SABATINO" id="2D61DEDD-E7D8-39F6-BCEF-AB4EF854D0AD">
<createdBy>padron</createdBy>
<createdTime>2019-07-05 12:28:54 UTC</createdTime>
<ownerDesignName>CES-FUNDAUC</ownerDesignName>
</ColumnProxy>
<ColumnProxy name="NOCTURNO" id="586E8039-D6FA-CB8E-420B-44D93A5CB178">
<createdBy>padron</createdBy>
<createdTime>2019-07-05 12:28:54 UTC</createdTime>
<ownerDesignName>CES-FUNDAUC</ownerDesignName>
</ColumnProxy>
<ColumnProxy name="CUOTAS" id="5D77A5FE-A428-CA93-F13F-3EFE4C1C7DA6">
<createdBy>padron</createdBy>
<createdTime>2019-07-05 12:28:54 UTC</createdTime>
<ownerDesignName>CES-FUNDAUC</ownerDesignName>
</ColumnProxy>
<ColumnProxy name="DESCRIPCION" id="78D8EB02-C75A-8DBF-D9A7-185BDD0F934E">
<createdBy>padron</createdBy>
<createdTime>2019-07-05 12:28:54 UTC</createdTime>
<ownerDesignName>CES-FUNDAUC</ownerDesignName>
</ColumnProxy>
<ColumnProxy name="ID_CALENDARIO" id="8E75ACE3-42BA-6E00-DF8E-589F0A2B9F56">
<createdBy>padron</createdBy>
<createdTime>2019-07-05 12:28:54 UTC</createdTime>
<ownerDesignName>CES-FUNDAUC</ownerDesignName>
</ColumnProxy>
<ColumnProxy name="NIVELES" id="92935575-D911-22C7-08F1-A1806278DC3C">
<createdBy>padron</createdBy>
<createdTime>2019-07-05 12:28:54 UTC</createdTime>
<ownerDesignName>CES-FUNDAUC</ownerDesignName>
</ColumnProxy>
<ColumnProxy name="IDIOMA" id="A751F54D-D060-C58D-B6BF-77C27B415BF4">
<createdBy>padron</createdBy>
<createdTime>2019-07-05 12:28:54 UTC</createdTime>
<ownerDesignName>CES-FUNDAUC</ownerDesignName>
</ColumnProxy>
<ColumnProxy name="ID_METODO" id="CEC23256-843A-4D04-86A2-4C096921063F">
<createdBy>padron</createdBy>
<createdTime>2019-07-05 12:28:54 UTC</createdTime>
<ownerDesignName>CES-FUNDAUC</ownerDesignName>
</ColumnProxy>
<ColumnProxy name="PROG_ACADEMICO" id="F6179C62-C27E-8CCE-688D-AEA750538F09">
<createdBy>padron</createdBy>
<createdTime>2019-07-05 12:28:54 UTC</createdTime>
<ownerDesignName>CES-FUNDAUC</ownerDesignName>
</ColumnProxy>
<ColumnProxy name="DIURNO" id="FB7DE6AC-0110-7D69-72CA-3A5F0B49E0C4">
<createdBy>padron</createdBy>
<createdTime>2019-07-05 12:28:54 UTC</createdTime>
<ownerDesignName>CES-FUNDAUC</ownerDesignName>
</ColumnProxy>
</columnProxies>
<indexProxies>
<IndexProxy class="oracle.dbtools.crest.model.design.storage.oracle.v10g.IndexProxyOraclev10g" name="PK_METODO" id="9C28EC24-76B1-7B7A-AA27-F099013CE52D">
<createdBy>padron</createdBy>
<createdTime>2019-07-05 12:28:56 UTC</createdTime>
<ownerDesignName>CES-FUNDAUC</ownerDesignName>
<schemaObject>FCF41941-BA25-8770-CD3F-F4AB582A1881</schemaObject>
<segment>A55AB7C9-E9D8-B030-A453-882A58461253</segment>
<tableSpace>C6CAF53F-0023-9370-2192-887C9EC71552</tableSpace>
</IndexProxy>
</indexProxies>
<primaryKeys>
<PrimaryKey class="oracle.dbtools.crest.model.design.storage.oracle.v10g.PKProxyOraclev10g" name="PK_METODO" id="86E9CE1E-AFE3-3C26-86D8-F88853C4CC70">
<createdBy>padron</createdBy>
<createdTime>2019-07-05 12:28:58 UTC</createdTime>
<ownerDesignName>CES-FUNDAUC</ownerDesignName>
<segment>A55AB7C9-E9D8-B030-A453-882A58461253</segment>
<tableSpace>C6CAF53F-0023-9370-2192-887C9EC71552</tableSpace>
<existingIndex>9C28EC24-76B1-7B7A-AA27-F099013CE52D</existingIndex>
<indexSegment>A55AB7C9-E9D8-B030-A453-882A58461253</indexSegment>
<indexSort>SORTED</indexSort>
<usingIndex>BY INDEX NAME</usingIndex>
</PrimaryKey>
</primaryKeys>
</TableProxyOraclev12c>